xdccshlf/__init__.py
xdccshlf/artificial_data.py
xdccshlf/skeleton.py
XDCCSHLF-1.1.dist-info/AUTHORS.rst
XDCCSHLF-1.1.dist-info/LICENSE.txt
XDCCSHLF-1.1.dist-info/METADATA
XDCCSHLF-1.1.dist-info/WHEEL
XDCCSHLF-1.1.dist-info/top_level.txt
XDCCSHLF-1.1.dist-info/RECORD
